{
    "key": "group_614f19d95c5ce",
    "title": "Block: Zahlen und Fakten",
    "fields": [
        {
            "key": "field_614f48a0755b2",
            "label": "Zahlen und Fakten",
            "name": "block_fact_figures",
            "type": "repeater",
            "instructions": "",
            "required": 1,
            "conditional_logic": 0,
            "wrapper": {
                "width": "",
                "class": "",
                "id": ""
            },
            "acfe_repeater_stylised_button": 0,
            "collapsed": "",
            "min": 1,
            "max": 0,
            "layout": "block",
            "button_label": "Inhalt hinzufügen",
            "wpml_cf_preferences": 1,
            "sub_fields": [
                {
                    "key": "field_614f48cf755b3",
                    "label": "Intro Text",
                    "name": "intro_txt",
                    "type": "text",
                    "instructions": "",
                    "required": 1,
                    "conditional_logic": 0,
                    "wrapper": {
                        "width": "",
                        "class": "",
                        "id": ""
                    },
                    "wpml_cf_preferences": 1,
                    "default_value": "",
                    "placeholder": "",
                    "prepend": "",
                    "append": "",
                    "maxlength": ""
                },
                {
                    "key": "field_614f48e0755b4",
                    "label": "Zahl",
                    "name": "number",
                    "type": "text",
                    "instructions": "",
                    "required": 1,
                    "conditional_logic": 0,
                    "wrapper": {
                        "width": "",
                        "class": "",
                        "id": ""
                    },
                    "wpml_cf_preferences": 1,
                    "default_value": "",
                    "placeholder": "",
                    "prepend": "",
                    "append": "",
                    "maxlength": ""
                },
                {
                    "key": "field_614f48ef755b5",
                    "label": "Text",
                    "name": "txt",
                    "type": "wysiwyg",
                    "instructions": "",
                    "required": 1,
                    "conditional_logic": 0,
                    "wrapper": {
                        "width": "",
                        "class": "",
                        "id": ""
                    },
                    "default_value": "",
                    "tabs": "all",
                    "toolbar": "full",
                    "media_upload": 0,
                    "delay": 0,
                    "wpml_cf_preferences": 1
                }
            ]
        },
        {
            "key": "field_614f5af284a27",
            "label": "Text unter der Uhr",
            "name": "block_fact_clock",
            "type": "text",
            "instructions": "",
            "required": 1,
            "conditional_logic": 0,
            "wrapper": {
                "width": "",
                "class": "",
                "id": ""
            },
            "wpml_cf_preferences": 1,
            "default_value": "",
            "placeholder": "",
            "prepend": "",
            "append": "",
            "maxlength": ""
        }
    ],
    "location": [
        [
            {
                "param": "block",
                "operator": "==",
                "value": "acf\/facts-and-figures"
            }
        ]
    ],
    "menu_order": 0,
    "position": "normal",
    "style": "default",
    "label_placement": "left",
    "instruction_placement": "label",
    "hide_on_screen": "",
    "active": true,
    "description": "",
    "acfe_display_title": "",
    "acfe_autosync": [
        "json"
    ],
    "acfe_form": 0,
    "acfe_meta": "",
    "acfe_note": "",
    "modified": 1632590594
}